{
    "YouTube": [
        {
            "AD Name": "Google Ads | Interested Kharidaar Laaye Har Baar with #GoogleAds",
            "Thumbnail": "https://i.ytimg.com/vi/LxSf5-4JtJc/maxresdefault.jpg",
            "Source URL": "https://youtu.be/LxSf5-4JtJc",
            "Date": "05/14/2021, 19:47:43"
        },
        {
            "AD Name": "How Compelling Is Your Writing?",
            "Thumbnail": "https://i.ytimg.com/vi/zADj0k0waFY/hqdefault.jpg?sqp=-oaymwEjCNACELwBSFryq4qpAxUIARUAAAAAGAElAADIQj0AgKJDeAE=&rs=AOn4CLDWypTDcCvO1Q0DbGgklBV-A40RdA",
            "Source URL": "https://youtu.be/zADj0k0waFY",
            "Date": "05/14/2021, 20:41:06"
        },
        {
            "AD Name": "Deep conversation between father & daughter | Leo & Lilly |Leo The Beagle",
            "Thumbnail": "https://i.ytimg.com/vi/vn1-YU8n_MU/maxresdefault.jpg",
            "Source URL": "https://youtu.be/vn1-YU8n_MU",
            "Date": "05/14/2021, 20:43:15"
        },
        {
            "AD Name": "Break the chain of transmission (in Hindi)",
            "Thumbnail": "https://i.ytimg.com/vi/Ld4fUV_PjPk/hqdefault.jpg?sqp=-oaymwEjCNACELwBSFryq4qpAxUIARUAAAAAGAElAADIQj0AgKJDeAE=&rs=AOn4CLClJupxtavr7_ORpybbH5zwt_-p9w",
            "Source URL": "https://youtu.be/Ld4fUV_PjPk?list=PLZnxqowr6IKjTAkRah5Ps58fBnoKx-37K",
            "Date": "05/14/2021, 21:05:41"
        },
        {
            "AD Name": "How Compelling Is Your Writing?",
            "Thumbnail": "https://i.ytimg.com/vi/zADj0k0waFY/hqdefault.jpg?sqp=-oaymwEjCNACELwBSFryq4qpAxUIARUAAAAAGAElAADIQj0AgKJDeAE=&rs=AOn4CLDWypTDcCvO1Q0DbGgklBV-A40RdA",
            "Source URL": "www.youtube.com/watch?v=zADj0k0waFY",
            "Date": "05/14/2021, 21:24:23"
        },
        {
            "AD Name": "How Compelling Is Your Writing?",
            "Thumbnail": "https://i.ytimg.com/vi/zADj0k0waFY/hqdefault.jpg?sqp=-oaymwEjCNACELwBSFryq4qpAxUIARUAAAAAGAElAADIQj0AgKJDeAE=&rs=AOn4CLDWypTDcCvO1Q0DbGgklBV-A40RdA",
            "Source URL": "www.youtube.com/watch?v=zADj0k0waFY\n",
            "Date": "05/15/2021, 14:44:43"
        }
    ]
}